license.S.HTML
venue.S.HTML
somatic/___itinerary/itinerary.S.HTML
somatic/___itinerary/possibilities.S.HTML
somatic/__book/neem--art-1163780_1920.png
somatic/__init__.py
somatic/__license/license.s.HTML
somatic/__license/licenses/gpl-3.0-standalone.html
somatic/_bin/somatic_1
somatic/_clique.py
somatic/_controls/flask/__init__.py
somatic/_controls/sanic/__init__.py
somatic/_status/checks/1/shares/shares 1.s.HTML
somatic/_status/checks/1/shares/shares 2.s.HTML
somatic/_status/checks/1/status_1.py
somatic/_status/status.proc.py
somatic/climate/__init__.py
somatic/module.MD
somatic/module.s.HTML
somatic/modules/HTML/__init__.py
somatic/modules/HTML_templates/template_1.py
somatic/modules/add_glob_to_paths.py
somatic/modules/parse_extensions.py
somatic/modules/port_in_use.py
somatic/modules/themes/themes.S.HTML
somatic/modules_ES/address/address.s.HTML
somatic/moves/start.py
somatic/start.proc.py
somatic-3.0.3.dist-info/METADATA
somatic-3.0.3.dist-info/WHEEL
somatic-3.0.3.dist-info/entry_points.txt
somatic-3.0.3.dist-info/RECORD
