Metadata-Version: 2.1
Name: somatic
Version: 3.0.3
Summary: The best documentation framework every created.
License: GPL-3.0-only
Keywords: documentation
Requires-Python: >=3.10,<4.0
Classifier: License :: OSI Approved :: GNU General Public License v3 (GPLv3)
Classifier: Programming Language :: Python :: 3
Classifier: Programming Language :: Python :: 3.10
Classifier: Programming Language :: Python :: 3.11
Classifier: Programming Language :: Python :: 3.12
Requires-Dist: biotech (>=1.0.3,<2.0.0)
Requires-Dist: click (>=8.1.7,<9.0.0)
Requires-Dist: flask (>=3.0.3,<4.0.0)
Requires-Dist: jsonschema (>=4.21.1,<5.0.0)
Requires-Dist: law-dictionary (>=1.0.11,<2.0.0)
Requires-Dist: mako (>=1.3.3,<2.0.0)
Requires-Dist: rich (>=13.7.1,<14.0.0)
Requires-Dist: sanic (>=23.12.1,<24.0.0)
Project-URL: GitLab, https://gitlab.com/offline-money/squash-1/somatic
